b3cotahist.py
b3cotahist-0.1.10.dist-info/METADATA
b3cotahist-0.1.10.dist-info/WHEEL
b3cotahist-0.1.10.dist-info/RECORD
