Metadata-Version: 2.1
Name: b3cotahist
Version: 0.1.10
Summary: Uma biblioteca simples para facilitar a leitura e o parsing do arquivo COTAHIST da B3.
Home-page: https://github.com/renanmoretto/b3cotahist
Author: renanmoretto
Author-email: himynameisrenan@outlook.com
Classifier: Programming Language :: Python :: 2
Classifier: Programming Language :: Python :: 2.7
Classifier: Programming Language :: Python :: 3
Classifier: Programming Language :: Python :: 3.4
Classifier: Programming Language :: Python :: 3.5
Classifier: Programming Language :: Python :: 3.6
Classifier: Programming Language :: Python :: 3.7
Classifier: Programming Language :: Python :: 3.8
Classifier: Programming Language :: Python :: 3.9
Classifier: Programming Language :: Python :: 3.10
Classifier: Programming Language :: Python :: 3.11
Classifier: Programming Language :: Python :: 3.12
Project-URL: Repository, https://github.com/renanmoretto/b3cotahist
